{
  "_class": "shapePath",
  "booleanOperation": -1,
  "do_objectID": "2763C9E9-8B4C-421D-81BD-411C8EF34DA2",
  "edited": true,
  "exportOptions": {
    "_class": "exportOptions",
    "exportFormats": [
    ],
    "includedLayerIds": [
    ],
    "layerOptions": 0,
    "shouldTrim": false
  },
  "frame": {
    "_class": "rect",
    "constrainProportions": false,
    "height": 4.861431460913337,
    "width": 4.859999999999957,
    "x": 432.9676800000001,
    "y": 194.919094425322
  },
  "isFlippedHorizontal": false,
  "isFlippedVertical": false,
  "isLocked": false,
  "isVisible": true,
  "layerListExpandedType": 0,
  "name": "Path",
  "nameIsFixed": false,
  "path": {
    "_class": "path",
    "isClosed": true,
    "pointRadiusBehaviour": 1,
    "points": [
      {
        "_class": "curvePoint",
        "cornerRadius": 0,
        "curveFrom": "{0.0049999999999954525, 0.045000000000001705}",
        "curveMode": 1,
        "curveTo": "{0.0049999999999954525, 0.045000000000001705}",
        "hasCurveFrom": false,
        "hasCurveTo": false,
        "point": "{0.0049999999999954525, 0.045000000000001705}"
      },
      {
        "_class": "curvePoint",
        "cornerRadius": 0,
        "curveFrom": "{0.021000000000000796, 0.055000000000006821}",
        "curveMode": 1,
        "curveTo": "{0.021000000000000796, 0.055000000000006821}",
        "hasCurveFrom": false,
        "hasCurveTo": false,
        "point": "{0.021000000000000796, 0.055000000000006821}"
      },
      {
        "_class": "curvePoint",
        "cornerRadius": 0,
        "curveFrom": "{0.045000000000001705, 0.036000000000001364}",
        "curveMode": 1,
        "curveTo": "{0.045000000000001705, 0.036000000000001364}",
        "hasCurveFrom": false,
        "hasCurveTo": false,
        "point": "{0.045000000000001705, 0.036000000000001364}"
      },
      {
        "_class": "curvePoint",
        "cornerRadius": 0,
        "curveFrom": "{0.024000000000000909, 0}",
        "curveMode": 1,
        "curveTo": "{0.024000000000000909, 0}",
        "hasCurveFrom": false,
        "hasCurveTo": false,
        "point": "{0.024000000000000909, 0}"
      },
      {
        "_class": "curvePoint",
        "cornerRadius": 0,
        "curveFrom": "{0.0030000000000001137, 0.016000000000005343}",
        "curveMode": 1,
        "curveTo": "{0.0030000000000001137, 0.016000000000005343}",
        "hasCurveFrom": false,
        "hasCurveTo": false,
        "point": "{0.0030000000000001137, 0.016000000000005343}"
      },
      {
        "_class": "curvePoint",
        "cornerRadius": 0,
        "curveFrom": "{0, 0.025999999999996248}",
        "curveMode": 1,
        "curveTo": "{0, 0.025999999999996248}",
        "hasCurveFrom": false,
        "hasCurveTo": false,
        "point": "{0, 0.025999999999996248}"
      }
    ]
  },
  "resizingConstraint": 63,
  "resizingType": 0,
  "rotation": 0,
  "shouldBreakMaskChain": false
}