{
  "_class": "shapePath",
  "booleanOperation": -1,
  "do_objectID": "630B2527-176D-43CC-8C93-548D864C58E3",
  "edited": true,
  "exportOptions": {
    "_class": "exportOptions",
    "exportFormats": [
    ],
    "includedLayerIds": [
    ],
    "layerOptions": 0,
    "shouldTrim": false
  },
  "frame": {
    "_class": "rect",
    "constrainProportions": false,
    "height": 4.861431460913382,
    "width": 4.859999999999957,
    "x": 125.74764,
    "y": 10.58333629040846
  },
  "isFlippedHorizontal": false,
  "isFlippedVertical": false,
  "isLocked": false,
  "isVisible": true,
  "layerListExpandedType": 0,
  "name": "Path",
  "nameIsFixed": false,
  "path": {
    "_class": "path",
    "isClosed": true,
    "pointRadiusBehaviour": 1,
    "points": [
      {
        "_class": "curvePoint",
        "cornerRadius": 0,
        "curveFrom": "{0.043000000000006366, 0.23799999999999599}",
        "curveMode": 1,
        "curveTo": "{0.043000000000006366, 0.23799999999999599}",
        "hasCurveFrom": false,
        "hasCurveTo": false,
        "point": "{0.043000000000006366, 0.23799999999999599}"
      },
      {
        "_class": "curvePoint",
        "cornerRadius": 0,
        "curveFrom": "{0.15600000000000591, 0.22699999999999676}",
        "curveMode": 1,
        "curveTo": "{0.15600000000000591, 0.22699999999999676}",
        "hasCurveFrom": false,
        "hasCurveTo": false,
        "point": "{0.15600000000000591, 0.22699999999999676}"
      },
      {
        "_class": "curvePoint",
        "cornerRadius": 0,
        "curveFrom": "{0.25100000000000477, 0.23499999999999588}",
        "curveMode": 1,
        "curveTo": "{0.25100000000000477, 0.23499999999999588}",
        "hasCurveFrom": false,
        "hasCurveTo": false,
        "point": "{0.25100000000000477, 0.23499999999999588}"
      },
      {
        "_class": "curvePoint",
        "cornerRadius": 0,
        "curveFrom": "{0.27000000000000313, 0.33199999999999719}",
        "curveMode": 1,
        "curveTo": "{0.27000000000000313, 0.33199999999999719}",
        "hasCurveFrom": false,
        "hasCurveTo": false,
        "point": "{0.27000000000000313, 0.33199999999999719}"
      },
      {
        "_class": "curvePoint",
        "cornerRadius": 0,
        "curveFrom": "{0.31000000000000227, 0.3559999999999981}",
        "curveMode": 1,
        "curveTo": "{0.31000000000000227, 0.3559999999999981}",
        "hasCurveFrom": false,
        "hasCurveTo": false,
        "point": "{0.31000000000000227, 0.3559999999999981}"
      },
      {
        "_class": "curvePoint",
        "cornerRadius": 0,
        "curveFrom": "{0.33300000000000196, 0.35099999999999909}",
        "curveMode": 1,
        "curveTo": "{0.33300000000000196, 0.35099999999999909}",
        "hasCurveFrom": false,
        "hasCurveTo": false,
        "point": "{0.33300000000000196, 0.35099999999999909}"
      },
      {
        "_class": "curvePoint",
        "cornerRadius": 0,
        "curveFrom": "{0.3890000000000029, 0.31799999999999784}",
        "curveMode": 1,
        "curveTo": "{0.3890000000000029, 0.31799999999999784}",
        "hasCurveFrom": false,
        "hasCurveTo": false,
        "point": "{0.3890000000000029, 0.31799999999999784}"
      },
      {
        "_class": "curvePoint",
        "cornerRadius": 0,
        "curveFrom": "{0.42700000000000315, 0.28899999999999793}",
        "curveMode": 1,
        "curveTo": "{0.42700000000000315, 0.28899999999999793}",
        "hasCurveFrom": false,
        "hasCurveTo": false,
        "point": "{0.42700000000000315, 0.28899999999999793}"
      },
      {
        "_class": "curvePoint",
        "cornerRadius": 0,
        "curveFrom": "{0.44500000000000384, 0.28499999999999659}",
        "curveMode": 1,
        "curveTo": "{0.44500000000000384, 0.28499999999999659}",
        "hasCurveFrom": false,
        "hasCurveTo": false,
        "point": "{0.44500000000000384, 0.28499999999999659}"
      },
      {
        "_class": "curvePoint",
        "cornerRadius": 0,
        "curveFrom": "{0.46000000000000441, 0.31099999999999639}",
        "curveMode": 1,
        "curveTo": "{0.46000000000000441, 0.31099999999999639}",
        "hasCurveFrom": false,
        "hasCurveTo": false,
        "point": "{0.46000000000000441, 0.31099999999999639}"
      },
      {
        "_class": "curvePoint",
        "cornerRadius": 0,
        "curveFrom": "{0.46700000000000585, 0.36199999999999477}",
        "curveMode": 1,
        "curveTo": "{0.46700000000000585, 0.36199999999999477}",
        "hasCurveFrom": false,
        "hasCurveTo": false,
        "point": "{0.46700000000000585, 0.36199999999999477}"
      },
      {
        "_class": "curvePoint",
        "cornerRadius": 0,
        "curveFrom": "{0.4760000000000062, 0.37799999999999301}",
        "curveMode": 1,
        "curveTo": "{0.4760000000000062, 0.37799999999999301}",
        "hasCurveFrom": false,
        "hasCurveTo": false,
        "point": "{0.4760000000000062, 0.37799999999999301}"
      },
      {
        "_class": "curvePoint",
        "cornerRadius": 0,
        "curveFrom": "{0.53000000000000469, 0.41399999999999437}",
        "curveMode": 1,
        "curveTo": "{0.53000000000000469, 0.41399999999999437}",
        "hasCurveFrom": false,
        "hasCurveTo": false,
        "point": "{0.53000000000000469, 0.41399999999999437}"
      },
      {
        "_class": "curvePoint",
        "cornerRadius": 0,
        "curveFrom": "{0.55500000000000327, 0.4199999999999946}",
        "curveMode": 1,
        "curveTo": "{0.55500000000000327, 0.4199999999999946}",
        "hasCurveFrom": false,
        "hasCurveTo": false,
        "point": "{0.55500000000000327, 0.4199999999999946}"
      },
      {
        "_class": "curvePoint",
        "cornerRadius": 0,
        "curveFrom": "{0.62100000000000222, 0.41799999999999571}",
        "curveMode": 1,
        "curveTo": "{0.62100000000000222, 0.41799999999999571}",
        "hasCurveFrom": false,
        "hasCurveTo": false,
        "point": "{0.62100000000000222, 0.41799999999999571}"
      },
      {
        "_class": "curvePoint",
        "cornerRadius": 0,
        "curveFrom": "{0.66900000000000048, 0.45599999999999596}",
        "curveMode": 1,
        "curveTo": "{0.66900000000000048, 0.45599999999999596}",
        "hasCurveFrom": false,
        "hasCurveTo": false,
        "point": "{0.66900000000000048, 0.45599999999999596}"
      },
      {
        "_class": "curvePoint",
        "cornerRadius": 0,
        "curveFrom": "{0.71799999999999997, 0.4599999999999973}",
        "curveMode": 1,
        "curveTo": "{0.71799999999999997, 0.4599999999999973}",
        "hasCurveFrom": false,
        "hasCurveTo": false,
        "point": "{0.71799999999999997, 0.4599999999999973}"
      },
      {
        "_class": "curvePoint",
        "cornerRadius": 0,
        "curveFrom": "{0.74800000000000111, 0.44899999999999807}",
        "curveMode": 1,
        "curveTo": "{0.74800000000000111, 0.44899999999999807}",
        "hasCurveFrom": false,
        "hasCurveTo": false,
        "point": "{0.74800000000000111, 0.44899999999999807}"
      },
      {
        "_class": "curvePoint",
        "cornerRadius": 0,
        "curveFrom": "{0.77400000000000091, 0.42399999999999949}",
        "curveMode": 1,
        "curveTo": "{0.77400000000000091, 0.42399999999999949}",
        "hasCurveFrom": false,
        "hasCurveTo": false,
        "point": "{0.77400000000000091, 0.42399999999999949}"
      },
      {
        "_class": "curvePoint",
        "cornerRadius": 0,
        "curveFrom": "{0.8019999999999996, 0.39099999999999824}",
        "curveMode": 1,
        "curveTo": "{0.8019999999999996, 0.39099999999999824}",
        "hasCurveFrom": false,
        "hasCurveTo": false,
        "point": "{0.8019999999999996, 0.39099999999999824}"
      },
      {
        "_class": "curvePoint",
        "cornerRadius": 0,
        "curveFrom": "{0.82900000000000063, 0.34999999999999787}",
        "curveMode": 1,
        "curveTo": "{0.82900000000000063, 0.34999999999999787}",
        "hasCurveFrom": false,
        "hasCurveTo": false,
        "point": "{0.82900000000000063, 0.34999999999999787}"
      },
      {
        "_class": "curvePoint",
        "cornerRadius": 0,
        "curveFrom": "{0.84799999999999898, 0.31699999999999662}",
        "curveMode": 1,
        "curveTo": "{0.84799999999999898, 0.31699999999999662}",
        "hasCurveFrom": false,
        "hasCurveTo": false,
        "point": "{0.84799999999999898, 0.31699999999999662}"
      },
      {
        "_class": "curvePoint",
        "cornerRadius": 0,
        "curveFrom": "{0.87399999999999878, 0.24599999999999511}",
        "curveMode": 1,
        "curveTo": "{0.87399999999999878, 0.24599999999999511}",
        "hasCurveFrom": false,
        "hasCurveTo": false,
        "point": "{0.87399999999999878, 0.24599999999999511}"
      },
      {
        "_class": "curvePoint",
        "cornerRadius": 0,
        "curveFrom": "{0.87699999999999889, 0.22999999999999687}",
        "curveMode": 1,
        "curveTo": "{0.87699999999999889, 0.22999999999999687}",
        "hasCurveFrom": false,
        "hasCurveTo": false,
        "point": "{0.87699999999999889, 0.22999999999999687}"
      },
      {
        "_class": "curvePoint",
        "cornerRadius": 0,
        "curveFrom": "{0.86899999999999977, 0.21499999999999631}",
        "curveMode": 1,
        "curveTo": "{0.86899999999999977, 0.21499999999999631}",
        "hasCurveFrom": false,
        "hasCurveTo": false,
        "point": "{0.86899999999999977, 0.21499999999999631}"
      },
      {
        "_class": "curvePoint",
        "cornerRadius": 0,
        "curveFrom": "{0.85699999999999932, 0.21199999999999619}",
        "curveMode": 1,
        "curveTo": "{0.85699999999999932, 0.21199999999999619}",
        "hasCurveFrom": false,
        "hasCurveTo": false,
        "point": "{0.85699999999999932, 0.21199999999999619}"
      },
      {
        "_class": "curvePoint",
        "cornerRadius": 0,
        "curveFrom": "{0.86100000000000065, 0.14899999999999736}",
        "curveMode": 1,
        "curveTo": "{0.86100000000000065, 0.14899999999999736}",
        "hasCurveFrom": false,
        "hasCurveTo": false,
        "point": "{0.86100000000000065, 0.14899999999999736}"
      },
      {
        "_class": "curvePoint",
        "cornerRadius": 0,
        "curveFrom": "{0.85500000000000043, 0.11599999999999611}",
        "curveMode": 1,
        "curveTo": "{0.85500000000000043, 0.11599999999999611}",
        "hasCurveFrom": false,
        "hasCurveTo": false,
        "point": "{0.85500000000000043, 0.11599999999999611}"
      },
      {
        "_class": "curvePoint",
        "cornerRadius": 0,
        "curveFrom": "{0.83399999999999963, 0.078999999999997073}",
        "curveMode": 1,
        "curveTo": "{0.83399999999999963, 0.078999999999997073}",
        "hasCurveFrom": false,
        "hasCurveTo": false,
        "point": "{0.83399999999999963, 0.078999999999997073}"
      },
      {
        "_class": "curvePoint",
        "cornerRadius": 0,
        "curveFrom": "{0.81700000000000017, 0.015999999999998238}",
        "curveMode": 1,
        "curveTo": "{0.81700000000000017, 0.015999999999998238}",
        "hasCurveFrom": false,
        "hasCurveTo": false,
        "point": "{0.81700000000000017, 0.015999999999998238}"
      },
      {
        "_class": "curvePoint",
        "cornerRadius": 0,
        "curveFrom": "{0.77899999999999991, 0}",
        "curveMode": 1,
        "curveTo": "{0.77899999999999991, 0}",
        "hasCurveFrom": false,
        "hasCurveTo": false,
        "point": "{0.77899999999999991, 0}"
      },
      {
        "_class": "curvePoint",
        "cornerRadius": 0,
        "curveFrom": "{0.71600000000000108, 0.0019999999999988916}",
        "curveMode": 1,
        "curveTo": "{0.71600000000000108, 0.0019999999999988916}",
        "hasCurveFrom": false,
        "hasCurveTo": false,
        "point": "{0.71600000000000108, 0.0019999999999988916}"
      },
      {
        "_class": "curvePoint",
        "cornerRadius": 0,
        "curveFrom": "{0.66300000000000026, 0.012000000000000455}",
        "curveMode": 1,
        "curveTo": "{0.66300000000000026, 0.012000000000000455}",
        "hasCurveFrom": false,
        "hasCurveTo": false,
        "point": "{0.66300000000000026, 0.012000000000000455}"
      },
      {
        "_class": "curvePoint",
        "cornerRadius": 0,
        "curveFrom": "{0.55999999999999872, 0.045000000000001705}",
        "curveMode": 1,
        "curveTo": "{0.55999999999999872, 0.045000000000001705}",
        "hasCurveFrom": false,
        "hasCurveTo": false,
        "point": "{0.55999999999999872, 0.045000000000001705}"
      },
      {
        "_class": "curvePoint",
        "cornerRadius": 0,
        "curveFrom": "{0.51200000000000045, 0.072000000000002728}",
        "curveMode": 1,
        "curveTo": "{0.51200000000000045, 0.072000000000002728}",
        "hasCurveFrom": false,
        "hasCurveTo": false,
        "point": "{0.51200000000000045, 0.072000000000002728}"
      },
      {
        "_class": "curvePoint",
        "cornerRadius": 0,
        "curveFrom": "{0.45899999999999963, 0.084000000000003183}",
        "curveMode": 1,
        "curveTo": "{0.45899999999999963, 0.084000000000003183}",
        "hasCurveFrom": false,
        "hasCurveTo": false,
        "point": "{0.45899999999999963, 0.084000000000003183}"
      },
      {
        "_class": "curvePoint",
        "cornerRadius": 0,
        "curveFrom": "{0.34799999999999898, 0.072000000000002728}",
        "curveMode": 1,
        "curveTo": "{0.34799999999999898, 0.072000000000002728}",
        "hasCurveFrom": false,
        "hasCurveTo": false,
        "point": "{0.34799999999999898, 0.072000000000002728}"
      },
      {
        "_class": "curvePoint",
        "cornerRadius": 0,
        "curveFrom": "{0.23799999999999955, 0.084000000000003183}",
        "curveMode": 1,
        "curveTo": "{0.23799999999999955, 0.084000000000003183}",
        "hasCurveFrom": false,
        "hasCurveTo": false,
        "point": "{0.23799999999999955, 0.084000000000003183}"
      },
      {
        "_class": "curvePoint",
        "cornerRadius": 0,
        "curveFrom": "{0.1769999999999996, 0.09800000000000253}",
        "curveMode": 1,
        "curveTo": "{0.1769999999999996, 0.09800000000000253}",
        "hasCurveFrom": false,
        "hasCurveTo": false,
        "point": "{0.1769999999999996, 0.09800000000000253}"
      },
      {
        "_class": "curvePoint",
        "cornerRadius": 0,
        "curveFrom": "{0.083999999999999631, 0.12800000000000367}",
        "curveMode": 1,
        "curveTo": "{0.083999999999999631, 0.12800000000000367}",
        "hasCurveFrom": false,
        "hasCurveTo": false,
        "point": "{0.083999999999999631, 0.12800000000000367}"
      },
      {
        "_class": "curvePoint",
        "cornerRadius": 0,
        "curveFrom": "{0.024000000000000909, 0.16700000000000514}",
        "curveMode": 1,
        "curveTo": "{0.024000000000000909, 0.16700000000000514}",
        "hasCurveFrom": false,
        "hasCurveTo": false,
        "point": "{0.024000000000000909, 0.16700000000000514}"
      },
      {
        "_class": "curvePoint",
        "cornerRadius": 0,
        "curveFrom": "{0.010000000000001563, 0.18200000000000571}",
        "curveMode": 1,
        "curveTo": "{0.010000000000001563, 0.18200000000000571}",
        "hasCurveFrom": false,
        "hasCurveTo": false,
        "point": "{0.010000000000001563, 0.18200000000000571}"
      },
      {
        "_class": "curvePoint",
        "cornerRadius": 0,
        "curveFrom": "{0, 0.21800000000000708}",
        "curveMode": 1,
        "curveTo": "{0, 0.21800000000000708}",
        "hasCurveFrom": false,
        "hasCurveTo": false,
        "point": "{0, 0.21800000000000708}"
      },
      {
        "_class": "curvePoint",
        "cornerRadius": 0,
        "curveFrom": "{0, 0.23400000000000531}",
        "curveMode": 1,
        "curveTo": "{0, 0.23400000000000531}",
        "hasCurveFrom": false,
        "hasCurveTo": false,
        "point": "{0, 0.23400000000000531}"
      }
    ]
  },
  "resizingConstraint": 63,
  "resizingType": 0,
  "rotation": 0,
  "shouldBreakMaskChain": false
}