{
  "_class": "text",
  "attributedString": {
    "_class": "MSAttributedString",
    "archivedAttributedString": {
      "_archive": [
        {
          "$archiver": "NSKeyedArchiver",
          "$objects": [
            "$null",
            {
              "$class": {
                "UID": 20
              },
              "NSAttributes": {
                "UID": 3
              },
              "NSString": {
                "UID": 2
              }
            },
            "Lorem ipsum dolor sit amet, consectetur adipiscing elit. Cras dapibus vulputate diam eu pretium. Mauris elit orci, ultricies id fermentum vel, porta et eros. Vestibulum condimentum lectus in convallis feugiat. Sed vulputate fringilla felis. Aliquam ut arcu et dui feugiat scelerisque eu quis diam. Mauris placerat congue dui sit amet blandit. Phasellus condimentum libero vel velit auctor, sit amet tincidunt velit varius.\nMauris lacinia porta faucibus. Fusce eu est ac eros vulputate mollis in ac felis. Aenean commodo scelerisque mi sed imperdiet. Donec at hendrerit nisi, eget vestibulum nisi. Sed sit amet magna luctus, facilisis erat quis, sagittis ligula. Aenean dignissim velit quis leo consequat ultricies. Proin quis pretium justo. Vestibulum at eros nisl. Fusce lobortis erat ante, eu cursus sapien molestie at. Pellentesque placerat ante diam, et euismod lacus dictum vel. Phasellus vitae sollicitudin mi.\nIn pulvinar eleifend convallis. Suspendisse elit erat, venenatis eget ullamcorper ut, laoreet iaculis nisl. Sed porta, felis id rhoncus aliquet, quam ipsum pellentesque metus, in sodales quam nunc vitae risus. Quisque in venenatis massa. Phasellus neque risus, ornare quis nisl ultricies, ullamcorper consectetur orci. Suspendisse rhoncus orci odio, id faucibus ipsum tincidunt nec. Ut eget ante sit amet justo volutpat convallis vitae et augue. Phasellus sagittis cursus fermentum.",
            {
              "$class": {
                "UID": 19
              },
              "NS.keys": [
                {
                  "UID": 4
                },
                {
                  "UID": 5
                },
                {
                  "UID": 6
                }
              ],
              "NS.objects": [
                {
                  "UID": 7
                },
                {
                  "UID": 9
                },
                {
                  "UID": 11
                }
              ]
            },
            "NSColor",
            "NSParagraphStyle",
            "MSAttributedStringFontAttribute",
            {
              "$class": {
                "UID": 8
              },
              "NSColorSpace": 1,
              "NSRGB": {
                "data": "0.2902216315 0.2901752889 0.2902374566\u0000",
                "type": "Buffer"
              }
            },
            {
              "$classes": [
                "NSColor",
                "NSObject"
              ],
              "$classname": "NSColor"
            },
            {
              "$class": {
                "UID": 10
              },
              "NSAlignment": 4,
              "NSMaxLineHeight": 20,
              "NSMinLineHeight": 20,
              "NSParagraphSpacing": 10,
              "NSTabStops": {
                "UID": 0
              }
            },
            {
              "$classes": [
                "NSMutableParagraphStyle",
                "NSParagraphStyle",
                "NSObject"
              ],
              "$classname": "NSMutableParagraphStyle"
            },
            {
              "$class": {
                "UID": 18
              },
              "NSFontDescriptorAttributes": {
                "UID": 12
              }
            },
            {
              "$class": {
                "UID": 17
              },
              "NS.keys": [
                {
                  "UID": 13
                },
                {
                  "UID": 14
                }
              ],
              "NS.objects": [
                {
                  "UID": 15
                },
                {
                  "UID": 16
                }
              ]
            },
            "NSFontSizeAttribute",
            "NSFontNameAttribute",
            14,
            "AvenirNext-Regular",
            {
              "$classes": [
                "NSMutableDictionary",
                "NSDictionary",
                "NSObject"
              ],
              "$classname": "NSMutableDictionary"
            },
            {
              "$classes": [
                "NSFontDescriptor",
                "NSObject"
              ],
              "$classname": "NSFontDescriptor"
            },
            {
              "$classes": [
                "NSDictionary",
                "NSObject"
              ],
              "$classname": "NSDictionary"
            },
            {
              "$classes": [
                "NSAttributedString",
                "NSObject"
              ],
              "$classname": "NSAttributedString"
            }
          ],
          "$top": {
            "root": {
              "UID": 1
            }
          },
          "$version": 100000
        }
      ]
    }
  },
  "automaticallyDrawOnUnderlyingPath": false,
  "do_objectID": "D5BB4201-5F51-4693-B1E0-4A4C88E1D33A",
  "dontSynchroniseWithSymbol": false,
  "exportOptions": {
    "_class": "exportOptions",
    "exportFormats": [
    ],
    "includedLayerIds": [
    ],
    "layerOptions": 0,
    "shouldTrim": false
  },
  "frame": {
    "_class": "rect",
    "constrainProportions": false,
    "do_objectID": "BA62F4AA-C23B-4135-89D5-F752C2EA3EB9",
    "height": 420,
    "width": 500,
    "x": 50,
    "y": 557
  },
  "glyphBounds": "{{0, 0}, {500, 420}}",
  "heightIsClipped": false,
  "isFlippedHorizontal": false,
  "isFlippedVertical": false,
  "isLocked": false,
  "isVisible": true,
  "layerListExpandedType": 0,
  "lineSpacingBehaviour": 0,
  "name": "Lorem ipsum dolor si",
  "nameIsFixed": false,
  "resizingConstraint": 63,
  "resizingType": 0,
  "rotation": 0,
  "shouldBreakMaskChain": false,
  "style": {
    "_class": "style",
    "do_objectID": "0C7A9E0D-F0AE-40BE-9D57-E2A63EAFEAE2",
    "endDecorationType": 0,
    "miterLimit": 10,
    "sharedObjectID": "DE7F560C-07DF-4A7C-A810-A51472C0BB67",
    "startDecorationType": 0,
    "textStyle": {
      "_class": "textStyle",
      "encodedAttributes": {
        "MSAttributedStringFontAttribute": {
          "_archive": [
            {
              "$archiver": "NSKeyedArchiver",
              "$objects": [
                "$null",
                {
                  "$class": {
                    "UID": 8
                  },
                  "NSFontDescriptorAttributes": {
                    "UID": 2
                  }
                },
                {
                  "$class": {
                    "UID": 7
                  },
                  "NS.keys": [
                    {
                      "UID": 3
                    },
                    {
                      "UID": 4
                    }
                  ],
                  "NS.objects": [
                    {
                      "UID": 5
                    },
                    {
                      "UID": 6
                    }
                  ]
                },
                "NSFontSizeAttribute",
                "NSFontNameAttribute",
                14,
                "AvenirNext-Regular",
                {
                  "$classes": [
                    "NSMutableDictionary",
                    "NSDictionary",
                    "NSObject"
                  ],
                  "$classname": "NSMutableDictionary"
                },
                {
                  "$classes": [
                    "NSFontDescriptor",
                    "NSObject"
                  ],
                  "$classname": "NSFontDescriptor"
                }
              ],
              "$top": {
                "root": {
                  "UID": 1
                }
              },
              "$version": 100000
            }
          ]
        },
        "NSColor": {
          "_archive": [
            {
              "$archiver": "NSKeyedArchiver",
              "$objects": [
                "$null",
                {
                  "$class": {
                    "UID": 2
                  },
                  "NSColorSpace": 1,
                  "NSRGB": {
                    "data": "0.2902216315 0.2901752889 0.2902374566\u0000",
                    "type": "Buffer"
                  }
                },
                {
                  "$classes": [
                    "NSColor",
                    "NSObject"
                  ],
                  "$classname": "NSColor"
                }
              ],
              "$top": {
                "root": {
                  "UID": 1
                }
              },
              "$version": 100000
            }
          ]
        },
        "NSParagraphStyle": {
          "_archive": [
            {
              "$archiver": "NSKeyedArchiver",
              "$objects": [
                "$null",
                {
                  "$class": {
                    "UID": 2
                  },
                  "NSAlignment": 4,
                  "NSMaxLineHeight": 20,
                  "NSMinLineHeight": 20,
                  "NSParagraphSpacing": 10,
                  "NSTabStops": {
                    "UID": 0
                  }
                },
                {
                  "$classes": [
                    "NSMutableParagraphStyle",
                    "NSParagraphStyle",
                    "NSObject"
                  ],
                  "$classname": "NSMutableParagraphStyle"
                }
              ],
              "$top": {
                "root": {
                  "UID": 1
                }
              },
              "$version": 100000
            }
          ]
        }
      }
    }
  },
  "textBehaviour": 1
}