{
  "_class": "shapePath",
  "booleanOperation": -1,
  "do_objectID": "0D8B2EF0-DF3A-4D17-B31A-A63FBC4CE51E",
  "edited": true,
  "exportOptions": {
    "_class": "exportOptions",
    "exportFormats": [
    ],
    "includedLayerIds": [
    ],
    "layerOptions": 0,
    "shouldTrim": false
  },
  "frame": {
    "_class": "rect",
    "constrainProportions": false,
    "height": 4.861431460913394,
    "width": 4.859999999999957,
    "x": 131.0110200000001,
    "y": 84.27777580639437
  },
  "isFlippedHorizontal": false,
  "isFlippedVertical": false,
  "isLocked": false,
  "isVisible": true,
  "layerListExpandedType": 0,
  "name": "Path",
  "nameIsFixed": false,
  "path": {
    "_class": "path",
    "isClosed": true,
    "pointRadiusBehaviour": 1,
    "points": [
      {
        "_class": "curvePoint",
        "cornerRadius": 0,
        "curveFrom": "{0.25499999999999901, 0.21399999999999153}",
        "curveMode": 1,
        "curveTo": "{0.25499999999999901, 0.21399999999999153}",
        "hasCurveFrom": false,
        "hasCurveTo": false,
        "point": "{0.25499999999999901, 0.21399999999999153}"
      },
      {
        "_class": "curvePoint",
        "cornerRadius": 0,
        "curveFrom": "{0.19299999999999784, 0.30799999999999272}",
        "curveMode": 1,
        "curveTo": "{0.19299999999999784, 0.30799999999999272}",
        "hasCurveFrom": false,
        "hasCurveTo": false,
        "point": "{0.19299999999999784, 0.30799999999999272}"
      },
      {
        "_class": "curvePoint",
        "cornerRadius": 0,
        "curveFrom": "{0.19999999999999929, 0.32899999999999352}",
        "curveMode": 1,
        "curveTo": "{0.19999999999999929, 0.32899999999999352}",
        "hasCurveFrom": false,
        "hasCurveTo": false,
        "point": "{0.19999999999999929, 0.32899999999999352}"
      },
      {
        "_class": "curvePoint",
        "cornerRadius": 0,
        "curveFrom": "{0.21399999999999864, 0.32799999999999585}",
        "curveMode": 1,
        "curveTo": "{0.21399999999999864, 0.32799999999999585}",
        "hasCurveFrom": false,
        "hasCurveTo": false,
        "point": "{0.21399999999999864, 0.32799999999999585}"
      },
      {
        "_class": "curvePoint",
        "cornerRadius": 0,
        "curveFrom": "{0.2619999999999969, 0.24699999999999278}",
        "curveMode": 1,
        "curveTo": "{0.2619999999999969, 0.24699999999999278}",
        "hasCurveFrom": false,
        "hasCurveTo": false,
        "point": "{0.2619999999999969, 0.24699999999999278}"
      },
      {
        "_class": "curvePoint",
        "cornerRadius": 0,
        "curveFrom": "{0.29099999999999682, 0.20499999999999119}",
        "curveMode": 1,
        "curveTo": "{0.29099999999999682, 0.20499999999999119}",
        "hasCurveFrom": false,
        "hasCurveTo": false,
        "point": "{0.29099999999999682, 0.20499999999999119}"
      },
      {
        "_class": "curvePoint",
        "cornerRadius": 0,
        "curveFrom": "{0.32599999999999696, 0.16099999999999426}",
        "curveMode": 1,
        "curveTo": "{0.32599999999999696, 0.16099999999999426}",
        "hasCurveFrom": false,
        "hasCurveTo": false,
        "point": "{0.32599999999999696, 0.16099999999999426}"
      },
      {
        "_class": "curvePoint",
        "cornerRadius": 0,
        "curveFrom": "{0.34099999999999753, 0.13699999999999335}",
        "curveMode": 1,
        "curveTo": "{0.34099999999999753, 0.13699999999999335}",
        "hasCurveFrom": false,
        "hasCurveTo": false,
        "point": "{0.34099999999999753, 0.13699999999999335}"
      },
      {
        "_class": "curvePoint",
        "cornerRadius": 0,
        "curveFrom": "{0.3349999999999973, 0.13299999999999557}",
        "curveMode": 1,
        "curveTo": "{0.3349999999999973, 0.13299999999999557}",
        "hasCurveFrom": false,
        "hasCurveTo": false,
        "point": "{0.3349999999999973, 0.13299999999999557}"
      },
      {
        "_class": "curvePoint",
        "cornerRadius": 0,
        "curveFrom": "{0.33399999999999608, 0.12499999999999289}",
        "curveMode": 1,
        "curveTo": "{0.33399999999999608, 0.12499999999999289}",
        "hasCurveFrom": false,
        "hasCurveTo": false,
        "point": "{0.33399999999999608, 0.12499999999999289}"
      },
      {
        "_class": "curvePoint",
        "cornerRadius": 0,
        "curveFrom": "{0.33799999999999741, 0.11299999999999244}",
        "curveMode": 1,
        "curveTo": "{0.33799999999999741, 0.11299999999999244}",
        "hasCurveFrom": false,
        "hasCurveTo": false,
        "point": "{0.33799999999999741, 0.11299999999999244}"
      },
      {
        "_class": "curvePoint",
        "cornerRadius": 0,
        "curveFrom": "{0.33899999999999864, 0.08899999999999153}",
        "curveMode": 1,
        "curveTo": "{0.33899999999999864, 0.08899999999999153}",
        "hasCurveFrom": false,
        "hasCurveTo": false,
        "point": "{0.33899999999999864, 0.08899999999999153}"
      },
      {
        "_class": "curvePoint",
        "cornerRadius": 0,
        "curveFrom": "{0.33199999999999719, 0.081999999999993634}",
        "curveMode": 1,
        "curveTo": "{0.33199999999999719, 0.081999999999993634}",
        "hasCurveFrom": false,
        "hasCurveTo": false,
        "point": "{0.33199999999999719, 0.081999999999993634}"
      },
      {
        "_class": "curvePoint",
        "cornerRadius": 0,
        "curveFrom": "{0.31299999999999883, 0.071999999999995623}",
        "curveMode": 1,
        "curveTo": "{0.31299999999999883, 0.071999999999995623}",
        "hasCurveFrom": false,
        "hasCurveTo": false,
        "point": "{0.31299999999999883, 0.071999999999995623}"
      },
      {
        "_class": "curvePoint",
        "cornerRadius": 0,
        "curveFrom": "{0.3089999999999975, 0.061999999999997613}",
        "curveMode": 1,
        "curveTo": "{0.3089999999999975, 0.061999999999997613}",
        "hasCurveFrom": false,
        "hasCurveTo": false,
        "point": "{0.3089999999999975, 0.061999999999997613}"
      },
      {
        "_class": "curvePoint",
        "cornerRadius": 0,
        "curveFrom": "{0.3089999999999975, 0.039999999999999147}",
        "curveMode": 1,
        "curveTo": "{0.3089999999999975, 0.039999999999999147}",
        "hasCurveFrom": false,
        "hasCurveTo": false,
        "point": "{0.3089999999999975, 0.039999999999999147}"
      },
      {
        "_class": "curvePoint",
        "cornerRadius": 0,
        "curveFrom": "{0.30299999999999727, 0.030999999999998806}",
        "curveMode": 1,
        "curveTo": "{0.30299999999999727, 0.030999999999998806}",
        "hasCurveFrom": false,
        "hasCurveTo": false,
        "point": "{0.30299999999999727, 0.030999999999998806}"
      },
      {
        "_class": "curvePoint",
        "cornerRadius": 0,
        "curveFrom": "{0.28999999999999559, 0.024999999999998579}",
        "curveMode": 1,
        "curveTo": "{0.28999999999999559, 0.024999999999998579}",
        "hasCurveFrom": false,
        "hasCurveTo": false,
        "point": "{0.28999999999999559, 0.024999999999998579}"
      },
      {
        "_class": "curvePoint",
        "cornerRadius": 0,
        "curveFrom": "{0.28299999999999415, 0.015000000000000568}",
        "curveMode": 1,
        "curveTo": "{0.28299999999999415, 0.015000000000000568}",
        "hasCurveFrom": false,
        "hasCurveTo": false,
        "point": "{0.28299999999999415, 0.015000000000000568}"
      },
      {
        "_class": "curvePoint",
        "cornerRadius": 0,
        "curveFrom": "{0.28299999999999415, 0.0020000000000024443}",
        "curveMode": 1,
        "curveTo": "{0.28299999999999415, 0.0020000000000024443}",
        "hasCurveFrom": false,
        "hasCurveTo": false,
        "point": "{0.28299999999999415, 0.0020000000000024443}"
      },
      {
        "_class": "curvePoint",
        "cornerRadius": 0,
        "curveFrom": "{0.27999999999999403, 0}",
        "curveMode": 1,
        "curveTo": "{0.27999999999999403, 0}",
        "hasCurveFrom": false,
        "hasCurveTo": false,
        "point": "{0.27999999999999403, 0}"
      },
      {
        "_class": "curvePoint",
        "cornerRadius": 0,
        "curveFrom": "{0.25399999999999423, 0.061999999999997613}",
        "curveMode": 1,
        "curveTo": "{0.25399999999999423, 0.061999999999997613}",
        "hasCurveFrom": false,
        "hasCurveTo": false,
        "point": "{0.25399999999999423, 0.061999999999997613}"
      },
      {
        "_class": "curvePoint",
        "cornerRadius": 0,
        "curveFrom": "{0.23399999999999466, 0.10099999999999909}",
        "curveMode": 1,
        "curveTo": "{0.23399999999999466, 0.10099999999999909}",
        "hasCurveFrom": false,
        "hasCurveTo": false,
        "point": "{0.23399999999999466, 0.10099999999999909}"
      },
      {
        "_class": "curvePoint",
        "cornerRadius": 0,
        "curveFrom": "{0.20699999999999363, 0.14499999999999602}",
        "curveMode": 1,
        "curveTo": "{0.20699999999999363, 0.14499999999999602}",
        "hasCurveFrom": false,
        "hasCurveTo": false,
        "point": "{0.20699999999999363, 0.14499999999999602}"
      },
      {
        "_class": "curvePoint",
        "cornerRadius": 0,
        "curveFrom": "{0.18199999999999505, 0.17299999999999471}",
        "curveMode": 1,
        "curveTo": "{0.18199999999999505, 0.17299999999999471}",
        "hasCurveFrom": false,
        "hasCurveTo": false,
        "point": "{0.18199999999999505, 0.17299999999999471}"
      },
      {
        "_class": "curvePoint",
        "cornerRadius": 0,
        "curveFrom": "{0.15799999999999415, 0.18499999999999517}",
        "curveMode": 1,
        "curveTo": "{0.15799999999999415, 0.18499999999999517}",
        "hasCurveFrom": false,
        "hasCurveTo": false,
        "point": "{0.15799999999999415, 0.18499999999999517}"
      },
      {
        "_class": "curvePoint",
        "cornerRadius": 0,
        "curveFrom": "{0.15499999999999403, 0.17899999999999494}",
        "curveMode": 1,
        "curveTo": "{0.15499999999999403, 0.17899999999999494}",
        "hasCurveFrom": false,
        "hasCurveTo": false,
        "point": "{0.15499999999999403, 0.17899999999999494}"
      },
      {
        "_class": "curvePoint",
        "cornerRadius": 0,
        "curveFrom": "{0.17299999999999471, 0.15499999999999403}",
        "curveMode": 1,
        "curveTo": "{0.17299999999999471, 0.15499999999999403}",
        "hasCurveFrom": false,
        "hasCurveTo": false,
        "point": "{0.17299999999999471, 0.15499999999999403}"
      },
      {
        "_class": "curvePoint",
        "cornerRadius": 0,
        "curveFrom": "{0.1909999999999954, 0.12599999999999056}",
        "curveMode": 1,
        "curveTo": "{0.1909999999999954, 0.12599999999999056}",
        "hasCurveFrom": false,
        "hasCurveTo": false,
        "point": "{0.1909999999999954, 0.12599999999999056}"
      },
      {
        "_class": "curvePoint",
        "cornerRadius": 0,
        "curveFrom": "{0.21999999999999531, 0.064999999999990621}",
        "curveMode": 1,
        "curveTo": "{0.21999999999999531, 0.064999999999990621}",
        "hasCurveFrom": false,
        "hasCurveTo": false,
        "point": "{0.21999999999999531, 0.064999999999990621}"
      },
      {
        "_class": "curvePoint",
        "cornerRadius": 0,
        "curveFrom": "{0.22799999999999443, 0.034999999999989484}",
        "curveMode": 1,
        "curveTo": "{0.22799999999999443, 0.034999999999989484}",
        "hasCurveFrom": false,
        "hasCurveTo": false,
        "point": "{0.22799999999999443, 0.034999999999989484}"
      },
      {
        "_class": "curvePoint",
        "cornerRadius": 0,
        "curveFrom": "{0.22799999999999443, 0.023999999999986699}",
        "curveMode": 1,
        "curveTo": "{0.22799999999999443, 0.023999999999986699}",
        "hasCurveFrom": false,
        "hasCurveTo": false,
        "point": "{0.22799999999999443, 0.023999999999986699}"
      },
      {
        "_class": "curvePoint",
        "cornerRadius": 0,
        "curveFrom": "{0.22599999999999554, 0.022999999999989029}",
        "curveMode": 1,
        "curveTo": "{0.22599999999999554, 0.022999999999989029}",
        "hasCurveFrom": false,
        "hasCurveTo": false,
        "point": "{0.22599999999999554, 0.022999999999989029}"
      },
      {
        "_class": "curvePoint",
        "cornerRadius": 0,
        "curveFrom": "{0.21999999999999531, 0.029999999999986926}",
        "curveMode": 1,
        "curveTo": "{0.21999999999999531, 0.029999999999986926}",
        "hasCurveFrom": false,
        "hasCurveTo": false,
        "point": "{0.21999999999999531, 0.029999999999986926}"
      },
      {
        "_class": "curvePoint",
        "cornerRadius": 0,
        "curveFrom": "{0.21300000000000097, 0.056999999999995055}",
        "curveMode": 1,
        "curveTo": "{0.21300000000000097, 0.056999999999995055}",
        "hasCurveFrom": false,
        "hasCurveTo": false,
        "point": "{0.21300000000000097, 0.056999999999995055}"
      },
      {
        "_class": "curvePoint",
        "cornerRadius": 0,
        "curveFrom": "{0.20100000000000051, 0.081999999999993634}",
        "curveMode": 1,
        "curveTo": "{0.20100000000000051, 0.081999999999993634}",
        "hasCurveFrom": false,
        "hasCurveTo": false,
        "point": "{0.20100000000000051, 0.081999999999993634}"
      },
      {
        "_class": "curvePoint",
        "cornerRadius": 0,
        "curveFrom": "{0.18299999999999983, 0.11699999999999733}",
        "curveMode": 1,
        "curveTo": "{0.18299999999999983, 0.11699999999999733}",
        "hasCurveFrom": false,
        "hasCurveTo": false,
        "point": "{0.18299999999999983, 0.11699999999999733}"
      },
      {
        "_class": "curvePoint",
        "cornerRadius": 0,
        "curveFrom": "{0.1509999999999998, 0.15299999999999869}",
        "curveMode": 1,
        "curveTo": "{0.1509999999999998, 0.15299999999999869}",
        "hasCurveFrom": false,
        "hasCurveTo": false,
        "point": "{0.1509999999999998, 0.15299999999999869}"
      },
      {
        "_class": "curvePoint",
        "cornerRadius": 0,
        "curveFrom": "{0.082999999999998408, 0.20699999999999363}",
        "curveMode": 1,
        "curveTo": "{0.082999999999998408, 0.20699999999999363}",
        "hasCurveFrom": false,
        "hasCurveTo": false,
        "point": "{0.082999999999998408, 0.20699999999999363}"
      },
      {
        "_class": "curvePoint",
        "cornerRadius": 0,
        "curveFrom": "{0.0049999999999990052, 0.28499999999999659}",
        "curveMode": 1,
        "curveTo": "{0.0049999999999990052, 0.28499999999999659}",
        "hasCurveFrom": false,
        "hasCurveTo": false,
        "point": "{0.0049999999999990052, 0.28499999999999659}"
      },
      {
        "_class": "curvePoint",
        "cornerRadius": 0,
        "curveFrom": "{0, 0.29399999999999693}",
        "curveMode": 1,
        "curveTo": "{0, 0.29399999999999693}",
        "hasCurveFrom": false,
        "hasCurveTo": false,
        "point": "{0, 0.29399999999999693}"
      },
      {
        "_class": "curvePoint",
        "cornerRadius": 0,
        "curveFrom": "{0.0030000000000001137, 0.30299999999999727}",
        "curveMode": 1,
        "curveTo": "{0.0030000000000001137, 0.30299999999999727}",
        "hasCurveFrom": false,
        "hasCurveTo": false,
        "point": "{0.0030000000000001137, 0.30299999999999727}"
      },
      {
        "_class": "curvePoint",
        "cornerRadius": 0,
        "curveFrom": "{0.021999999999998465, 0.31499999999999773}",
        "curveMode": 1,
        "curveTo": "{0.021999999999998465, 0.31499999999999773}",
        "hasCurveFrom": false,
        "hasCurveTo": false,
        "point": "{0.021999999999998465, 0.31499999999999773}"
      },
      {
        "_class": "curvePoint",
        "cornerRadius": 0,
        "curveFrom": "{0.064000000000000057, 0.28699999999999903}",
        "curveMode": 1,
        "curveTo": "{0.064000000000000057, 0.28699999999999903}",
        "hasCurveFrom": false,
        "hasCurveTo": false,
        "point": "{0.064000000000000057, 0.28699999999999903}"
      },
      {
        "_class": "curvePoint",
        "cornerRadius": 0,
        "curveFrom": "{0.14399999999999835, 0.21000000000000085}",
        "curveMode": 1,
        "curveTo": "{0.14399999999999835, 0.21000000000000085}",
        "hasCurveFrom": false,
        "hasCurveTo": false,
        "point": "{0.14399999999999835, 0.21000000000000085}"
      },
      {
        "_class": "curvePoint",
        "cornerRadius": 0,
        "curveFrom": "{0.14999999999999858, 0.20700000000000074}",
        "curveMode": 1,
        "curveTo": "{0.14999999999999858, 0.20700000000000074}",
        "hasCurveFrom": false,
        "hasCurveTo": false,
        "point": "{0.14999999999999858, 0.20700000000000074}"
      },
      {
        "_class": "curvePoint",
        "cornerRadius": 0,
        "curveFrom": "{0.16099999999999781, 0.21399999999999864}",
        "curveMode": 1,
        "curveTo": "{0.16099999999999781, 0.21399999999999864}",
        "hasCurveFrom": false,
        "hasCurveTo": false,
        "point": "{0.16099999999999781, 0.21399999999999864}"
      },
      {
        "_class": "curvePoint",
        "cornerRadius": 0,
        "curveFrom": "{0.1579999999999977, 0.22399999999999665}",
        "curveMode": 1,
        "curveTo": "{0.1579999999999977, 0.22399999999999665}",
        "hasCurveFrom": false,
        "hasCurveTo": false,
        "point": "{0.1579999999999977, 0.22399999999999665}"
      },
      {
        "_class": "curvePoint",
        "cornerRadius": 0,
        "curveFrom": "{0.05099999999999838, 0.3469999999999942}",
        "curveMode": 1,
        "curveTo": "{0.05099999999999838, 0.3469999999999942}",
        "hasCurveFrom": false,
        "hasCurveTo": false,
        "point": "{0.05099999999999838, 0.3469999999999942}"
      },
      {
        "_class": "curvePoint",
        "cornerRadius": 0,
        "curveFrom": "{0.10099999999999909, 0.31999999999999318}",
        "curveMode": 1,
        "curveTo": "{0.10099999999999909, 0.31999999999999318}",
        "hasCurveFrom": false,
        "hasCurveTo": false,
        "point": "{0.10099999999999909, 0.31999999999999318}"
      },
      {
        "_class": "curvePoint",
        "cornerRadius": 0,
        "curveFrom": "{0.12199999999999989, 0.32499999999999574}",
        "curveMode": 1,
        "curveTo": "{0.12199999999999989, 0.32499999999999574}",
        "hasCurveFrom": false,
        "hasCurveTo": false,
        "point": "{0.12199999999999989, 0.32499999999999574}"
      },
      {
        "_class": "curvePoint",
        "cornerRadius": 0,
        "curveFrom": "{0.13100000000000023, 0.32399999999999807}",
        "curveMode": 1,
        "curveTo": "{0.13100000000000023, 0.32399999999999807}",
        "hasCurveFrom": false,
        "hasCurveTo": false,
        "point": "{0.13100000000000023, 0.32399999999999807}"
      },
      {
        "_class": "curvePoint",
        "cornerRadius": 0,
        "curveFrom": "{0.1440000000000019, 0.31499999999999773}",
        "curveMode": 1,
        "curveTo": "{0.1440000000000019, 0.31499999999999773}",
        "hasCurveFrom": false,
        "hasCurveTo": false,
        "point": "{0.1440000000000019, 0.31499999999999773}"
      },
      {
        "_class": "curvePoint",
        "cornerRadius": 0,
        "curveFrom": "{0.16200000000000259, 0.29899999999999949}",
        "curveMode": 1,
        "curveTo": "{0.16200000000000259, 0.29899999999999949}",
        "hasCurveFrom": false,
        "hasCurveTo": false,
        "point": "{0.16200000000000259, 0.29899999999999949}"
      },
      {
        "_class": "curvePoint",
        "cornerRadius": 0,
        "curveFrom": "{0.24100000000000321, 0.19400000000000261}",
        "curveMode": 1,
        "curveTo": "{0.24100000000000321, 0.19400000000000261}",
        "hasCurveFrom": false,
        "hasCurveTo": false,
        "point": "{0.24100000000000321, 0.19400000000000261}"
      },
      {
        "_class": "curvePoint",
        "cornerRadius": 0,
        "curveFrom": "{0.25700000000000145, 0.17800000000000438}",
        "curveMode": 1,
        "curveTo": "{0.25700000000000145, 0.17800000000000438}",
        "hasCurveFrom": false,
        "hasCurveTo": false,
        "point": "{0.25700000000000145, 0.17800000000000438}"
      },
      {
        "_class": "curvePoint",
        "cornerRadius": 0,
        "curveFrom": "{0.26300000000000168, 0.19300000000000495}",
        "curveMode": 1,
        "curveTo": "{0.26300000000000168, 0.19300000000000495}",
        "hasCurveFrom": false,
        "hasCurveTo": false,
        "point": "{0.26300000000000168, 0.19300000000000495}"
      },
      {
        "_class": "curvePoint",
        "cornerRadius": 0,
        "curveFrom": "{0.26200000000000045, 0.20300000000000296}",
        "curveMode": 1,
        "curveTo": "{0.26200000000000045, 0.20300000000000296}",
        "hasCurveFrom": false,
        "hasCurveTo": false,
        "point": "{0.26200000000000045, 0.20300000000000296}"
      }
    ]
  },
  "resizingConstraint": 63,
  "resizingType": 0,
  "rotation": 0,
  "shouldBreakMaskChain": false
}