{
  "_class": "shapePath",
  "booleanOperation": -1,
  "do_objectID": "0EEF10CA-909D-42DB-8C4A-F56A36FA3BC3",
  "edited": true,
  "exportOptions": {
    "_class": "exportOptions",
    "exportFormats": [
    ],
    "includedLayerIds": [
    ],
    "layerOptions": 0,
    "shouldTrim": false
  },
  "frame": {
    "_class": "rect",
    "constrainProportions": false,
    "height": 4.861431460913368,
    "width": 4.8599999999999,
    "x": 366.14754,
    "y": 13.38352081189457
  },
  "isFlippedHorizontal": false,
  "isFlippedVertical": false,
  "isLocked": false,
  "isVisible": true,
  "layerListExpandedType": 0,
  "name": "Path",
  "nameIsFixed": false,
  "path": {
    "_class": "path",
    "isClosed": true,
    "pointRadiusBehaviour": 1,
    "points": [
      {
        "_class": "curvePoint",
        "cornerRadius": 0,
        "curveFrom": "{0.067999999999983629, 0.11899999999999622}",
        "curveMode": 1,
        "curveTo": "{0.067999999999983629, 0.11899999999999622}",
        "hasCurveFrom": false,
        "hasCurveTo": false,
        "point": "{0.067999999999983629, 0.11899999999999622}"
      },
      {
        "_class": "curvePoint",
        "cornerRadius": 0,
        "curveFrom": "{0.11099999999999, 0.17999999999999616}",
        "curveMode": 1,
        "curveTo": "{0.11099999999999, 0.17999999999999616}",
        "hasCurveFrom": false,
        "hasCurveTo": false,
        "point": "{0.11099999999999, 0.17999999999999616}"
      },
      {
        "_class": "curvePoint",
        "cornerRadius": 0,
        "curveFrom": "{0.1559999999999917, 0.22599999999999554}",
        "curveMode": 1,
        "curveTo": "{0.1559999999999917, 0.22599999999999554}",
        "hasCurveFrom": false,
        "hasCurveTo": false,
        "point": "{0.1559999999999917, 0.22599999999999554}"
      },
      {
        "_class": "curvePoint",
        "cornerRadius": 0,
        "curveFrom": "{0.19299999999999784, 0.29699999999999704}",
        "curveMode": 1,
        "curveTo": "{0.19299999999999784, 0.29699999999999704}",
        "hasCurveFrom": false,
        "hasCurveTo": false,
        "point": "{0.19299999999999784, 0.29699999999999704}"
      },
      {
        "_class": "curvePoint",
        "cornerRadius": 0,
        "curveFrom": "{0.20399999999999352, 0.32699999999999818}",
        "curveMode": 1,
        "curveTo": "{0.20399999999999352, 0.32699999999999818}",
        "hasCurveFrom": false,
        "hasCurveTo": false,
        "point": "{0.20399999999999352, 0.32699999999999818}"
      },
      {
        "_class": "curvePoint",
        "cornerRadius": 0,
        "curveFrom": "{0.24599999999999511, 0.38799999999999812}",
        "curveMode": 1,
        "curveTo": "{0.24599999999999511, 0.38799999999999812}",
        "hasCurveFrom": false,
        "hasCurveTo": false,
        "point": "{0.24599999999999511, 0.38799999999999812}"
      },
      {
        "_class": "curvePoint",
        "cornerRadius": 0,
        "curveFrom": "{0.3089999999999975, 0.37099999999999866}",
        "curveMode": 1,
        "curveTo": "{0.3089999999999975, 0.37099999999999866}",
        "hasCurveFrom": false,
        "hasCurveTo": false,
        "point": "{0.3089999999999975, 0.37099999999999866}"
      },
      {
        "_class": "curvePoint",
        "cornerRadius": 0,
        "curveFrom": "{0.33199999999999363, 0.33299999999999841}",
        "curveMode": 1,
        "curveTo": "{0.33199999999999363, 0.33299999999999841}",
        "hasCurveFrom": false,
        "hasCurveTo": false,
        "point": "{0.33199999999999363, 0.33299999999999841}"
      },
      {
        "_class": "curvePoint",
        "cornerRadius": 0,
        "curveFrom": "{0.32799999999998875, 0.30399999999999849}",
        "curveMode": 1,
        "curveTo": "{0.32799999999998875, 0.30399999999999849}",
        "hasCurveFrom": false,
        "hasCurveTo": false,
        "point": "{0.32799999999998875, 0.30399999999999849}"
      },
      {
        "_class": "curvePoint",
        "cornerRadius": 0,
        "curveFrom": "{0.28699999999999193, 0.26999999999999957}",
        "curveMode": 1,
        "curveTo": "{0.28699999999999193, 0.26999999999999957}",
        "hasCurveFrom": false,
        "hasCurveTo": false,
        "point": "{0.28699999999999193, 0.26999999999999957}"
      },
      {
        "_class": "curvePoint",
        "cornerRadius": 0,
        "curveFrom": "{0.26699999999999591, 0.23999999999999844}",
        "curveMode": 1,
        "curveTo": "{0.26699999999999591, 0.23999999999999844}",
        "hasCurveFrom": false,
        "hasCurveTo": false,
        "point": "{0.26699999999999591, 0.23999999999999844}"
      },
      {
        "_class": "curvePoint",
        "cornerRadius": 0,
        "curveFrom": "{0.24899999999999523, 0.15700000000000003}",
        "curveMode": 1,
        "curveTo": "{0.24899999999999523, 0.15700000000000003}",
        "hasCurveFrom": false,
        "hasCurveTo": false,
        "point": "{0.24899999999999523, 0.15700000000000003}"
      },
      {
        "_class": "curvePoint",
        "cornerRadius": 0,
        "curveFrom": "{0.22799999999999443, 0.14399999999999835}",
        "curveMode": 1,
        "curveTo": "{0.22799999999999443, 0.14399999999999835}",
        "hasCurveFrom": false,
        "hasCurveTo": false,
        "point": "{0.22799999999999443, 0.14399999999999835}"
      },
      {
        "_class": "curvePoint",
        "cornerRadius": 0,
        "curveFrom": "{0.14000000000000057, 0.1059999999999981}",
        "curveMode": 1,
        "curveTo": "{0.14000000000000057, 0.1059999999999981}",
        "hasCurveFrom": false,
        "hasCurveTo": false,
        "point": "{0.14000000000000057, 0.1059999999999981}"
      },
      {
        "_class": "curvePoint",
        "cornerRadius": 0,
        "curveFrom": "{0.10699999999999932, 0.081999999999997186}",
        "curveMode": 1,
        "curveTo": "{0.10699999999999932, 0.081999999999997186}",
        "hasCurveFrom": false,
        "hasCurveTo": false,
        "point": "{0.10699999999999932, 0.081999999999997186}"
      },
      {
        "_class": "curvePoint",
        "cornerRadius": 0,
        "curveFrom": "{0.049999999999997158, 0.030999999999998806}",
        "curveMode": 1,
        "curveTo": "{0.049999999999997158, 0.030999999999998806}",
        "hasCurveFrom": false,
        "hasCurveTo": false,
        "point": "{0.049999999999997158, 0.030999999999998806}"
      },
      {
        "_class": "curvePoint",
        "cornerRadius": 0,
        "curveFrom": "{0, 0}",
        "curveMode": 1,
        "curveTo": "{0, 0}",
        "hasCurveFrom": false,
        "hasCurveTo": false,
        "point": "{0, 0}"
      },
      {
        "_class": "curvePoint",
        "cornerRadius": 0,
        "curveFrom": "{0.034999999999996589, 0.071000000000001506}",
        "curveMode": 1,
        "curveTo": "{0.034999999999996589, 0.071000000000001506}",
        "hasCurveFrom": false,
        "hasCurveTo": false,
        "point": "{0.034999999999996589, 0.071000000000001506}"
      }
    ]
  },
  "resizingConstraint": 63,
  "resizingType": 0,
  "rotation": 0,
  "shouldBreakMaskChain": false
}